pulumi_aws_acm/__init__.py
pulumi_aws_acm/tests.py
pulumi_aws_acm-0.1.1.data/data/requirements.txt
pulumi_aws_acm-0.1.1.dist-info/LICENSE
pulumi_aws_acm-0.1.1.dist-info/METADATA
pulumi_aws_acm-0.1.1.dist-info/WHEEL
pulumi_aws_acm-0.1.1.dist-info/top_level.txt
pulumi_aws_acm-0.1.1.dist-info/RECORD
