Metadata-Version: 2.1
Name: pulumi-aws-acm
Version: 0.1.1
Summary: Pulumi ComponentResource for create ACM Certificate and validate it with DNS validation method
Home-page: https://github.com/jetbrains-infra/pulumi-aws-acm
Author: Vadim Reyder
Author-email: vadim.reyder@gmail.com
License: MIT
Platform: UNKNOWN
License-File: LICENSE
Requires-Dist: pulumi (<4.0.0,>=3.0.0)
Requires-Dist: pulumi-aws (<5.0.0,>=4.0.0)
